LICENSE
MANIFEST.in
README.md
pyproject.toml
setup.cfg
setup.py
ph4_acmd2.egg-info/PKG-INFO
ph4_acmd2.egg-info/SOURCES.txt
ph4_acmd2.egg-info/dependency_links.txt
ph4_acmd2.egg-info/requires.txt
ph4_acmd2.egg-info/top_level.txt
ph4acmd2/__init__.py